xitroo/Api.py
xitroo/__init__.py
xitroo_api-0.0.1.dist-info/LICENSE.txt
xitroo_api-0.0.1.dist-info/METADATA
xitroo_api-0.0.1.dist-info/WHEEL
xitroo_api-0.0.1.dist-info/top_level.txt
xitroo_api-0.0.1.dist-info/RECORD
