Metadata-Version: 2.1
Name: xitroo-api
Version: 0.0.1
Summary: Xitroo Temporarily Email Api
Home-page: https://github.com/TheMythFlex
Author: TheMythFlex
Author-email: flextools.co@gmail.com
Classifier: Programming Language :: Python :: 3
Classifier: License :: OSI Approved :: MIT License
Classifier: Operating System :: OS Independent
Requires-Python: >=3.6
License-File: LICENSE.txt
